temporal_sqlalchemy/__init__.py
temporal_sqlalchemy/bases.py
temporal_sqlalchemy/clock.py
temporal_sqlalchemy/core.py
temporal_sqlalchemy/metadata.py
temporal_sqlalchemy/nine.py
temporal_sqlalchemy/session.py
temporal_sqlalchemy/util.py
temporal_sqlalchemy/version.py
temporal_sqlalchemy/tests/__init__.py
temporal_sqlalchemy/tests/conftest.py
temporal_sqlalchemy/tests/models.py
temporal_sqlalchemy/tests/shared.py
temporal_sqlalchemy/tests/test_builders.py
temporal_sqlalchemy/tests/test_concrete_base.py
temporal_sqlalchemy/tests/test_edge_cases.py
temporal_sqlalchemy/tests/test_invariants.py
temporal_sqlalchemy/tests/test_joined_table_inheritance.py
temporal_sqlalchemy/tests/test_persist_changes_on_commit.py
temporal_sqlalchemy/tests/test_session.py
temporal_sqlalchemy/tests/test_temporal_model_mixin.py
temporal_sqlalchemy/tests/test_temporal_models.py
temporal_sqlalchemy/tests/test_temporal_models_with_relationships.py
temporal_sqlalchemy/tests/test_temporal_multi_entity_with_activity.py
temporal_sqlalchemy/tests/test_temporal_with_activity.py
temporal_sqlalchemy-0.5.0.dist-info/DESCRIPTION.rst
temporal_sqlalchemy-0.5.0.dist-info/METADATA
temporal_sqlalchemy-0.5.0.dist-info/RECORD
temporal_sqlalchemy-0.5.0.dist-info/WHEEL
temporal_sqlalchemy-0.5.0.dist-info/metadata.json
temporal_sqlalchemy-0.5.0.dist-info/pbr.json
temporal_sqlalchemy-0.5.0.dist-info/top_level.txt
